glam4cm/__init__.py
glam4cm/run.py
glam4cm/run_conf_v2.py
glam4cm/run_configs.py
glam4cm/run_confs.py
glam4cm/settings.py
glam4cm/utils.py
glam4cm/data_loading/__init__.py
glam4cm/data_loading/data.py
glam4cm/data_loading/encoding.py
glam4cm/data_loading/graph_dataset.py
glam4cm/data_loading/metadata.py
glam4cm/data_loading/models_dataset.py
glam4cm/data_loading/utils.py
glam4cm/downstream_tasks/__init__.py
glam4cm/downstream_tasks/bert_edge_classification.py
glam4cm/downstream_tasks/bert_graph_classification.py
glam4cm/downstream_tasks/bert_graph_classification_comp.py
glam4cm/downstream_tasks/bert_link_prediction.py
glam4cm/downstream_tasks/bert_node_classification.py
glam4cm/downstream_tasks/cm_gpt_edge_classification.py
glam4cm/downstream_tasks/cm_gpt_node_classification.py
glam4cm/downstream_tasks/cm_gpt_pretraining.py
glam4cm/downstream_tasks/common_args.py
glam4cm/downstream_tasks/create_dataset.py
glam4cm/downstream_tasks/gnn_edge_classification.py
glam4cm/downstream_tasks/gnn_graph_cls.py
glam4cm/downstream_tasks/gnn_link_prediction.py
glam4cm/downstream_tasks/gnn_node_classification.py
glam4cm/downstream_tasks/tf_idf_text_classification.py
glam4cm/downstream_tasks/utils.py
glam4cm/downstream_tasks/word2vec_text_classification.py
glam4cm/embeddings/__init__.py
glam4cm/embeddings/bert.py
glam4cm/embeddings/common.py
glam4cm/embeddings/fasttext.py
glam4cm/embeddings/tfidf.py
glam4cm/embeddings/w2v.py
glam4cm/encoding/__init__.py
glam4cm/encoding/common.py
glam4cm/encoding/encoders.py
glam4cm/graph2str/__init__.py
glam4cm/graph2str/common.py
glam4cm/graph2str/constants.py
glam4cm/graph2str/ontouml.py
glam4cm/graph2str/uml.py
glam4cm/lang2graph/__init__.py
glam4cm/lang2graph/archimate.py
glam4cm/lang2graph/bpmn.py
glam4cm/lang2graph/common.py
glam4cm/lang2graph/ecore.py
glam4cm/lang2graph/ontouml.py
glam4cm/lang2graph/utils.py
glam4cm/models/cmgpt.py
glam4cm/models/gnn_layers.py
glam4cm/models/hf.py
glam4cm/tokenization/__init__.py
glam4cm-1.0.1.dist-info/licenses/LICENSE
glam4cm-1.0.1.dist-info/METADATA
glam4cm-1.0.1.dist-info/WHEEL
glam4cm-1.0.1.dist-info/entry_points.txt
glam4cm-1.0.1.dist-info/top_level.txt
glam4cm-1.0.1.dist-info/RECORD
