Metadata-Version: 2.4
Name: glam4cm
Version: 1.0.1
Summary: Graph Neural Networks and Language Models Trainer (Separate or combined) for conceptual models
Author-email: Syed Juned Ali <syed.juned.ali@tuwien.ac.at>
License: MIT License
Project-URL: Homepage, https://github.com/junaidiiith/glam4cm
Project-URL: Issues, https://github.com/junaidiiith/glam4cm/issues
Requires-Python: >=3.8
License-File: LICENSE
Requires-Dist: langchain-text-splitters
Requires-Dist: scikit-learn
Requires-Dist: scipy
Requires-Dist: torch
Requires-Dist: numpy
Requires-Dist: transformers
Requires-Dist: sentence-transformers
Requires-Dist: tqdm
Requires-Dist: networkx
Requires-Dist: torch_geometric
Requires-Dist: pandas
Requires-Dist: tensorboardX
Requires-Dist: xmltodict
Requires-Dist: fasttext
Provides-Extra: dev
Requires-Dist: pytest; extra == "dev"
Requires-Dist: black; extra == "dev"
Dynamic: license-file
